sentence_mixing/__init__.py
sentence_mixing/config.py
sentence_mixing/parameter_optimizer.py
sentence_mixing/sentence_mixer.py
sentence_mixing/serialize.py
sentence_mixing/logic/analyze.py
sentence_mixing/logic/analyze_step_1.py
sentence_mixing/logic/analyze_step_2.py
sentence_mixing/logic/analyze_step_3.py
sentence_mixing/logic/audio_analysis.py
sentence_mixing/logic/display.py
sentence_mixing/logic/global_audio_data.py
sentence_mixing/logic/parameters.py
sentence_mixing/logic/randomizer.py
sentence_mixing/logic/text_parser.py
sentence_mixing/logic/utils.py
sentence_mixing/logic/video_processing.py
sentence_mixing/model/abstract.py
sentence_mixing/model/association.py
sentence_mixing/model/audio.py
sentence_mixing/model/choice.py
sentence_mixing/model/exceptions.py
sentence_mixing/model/scorable.py
sentence_mixing/model/target.py
sentence_mixing/model/video.py
sentence_mixing/parameter_tuning/parameter_tweaking.py
sentence_mixing/parameter_tuning/scoring.py
sentence_mixing/parameter_tuning/speech_to_text_dict.py
sentence_mixing/video_creator/audio.py
sentence_mixing/video_creator/download.py
sentence_mixing/video_creator/video.py
sentence_mixing-2.0.4.dist-info/LICENSE
sentence_mixing-2.0.4.dist-info/METADATA
sentence_mixing-2.0.4.dist-info/WHEEL
sentence_mixing-2.0.4.dist-info/top_level.txt
sentence_mixing-2.0.4.dist-info/RECORD
