Metadata-Version: 2.1
Name: sentence-mixing
Version: 2.0.4
Summary: Sentence mixing library
Home-page: https://github.com/pop123123123/sentence-mixing
Author: Nicolas BUSSER, Louis MOUHAT
Author-email: nicolas.busser67@gmail.com
Classifier: Programming Language :: Python :: 3
Classifier: License :: OSI Approved :: MIT License
Classifier: Operating System :: OS Independent
Requires-Python: >=3.6
License-File: LICENSE
Requires-Dist: textgrid
Requires-Dist: yt-dlp
Requires-Dist: num2words
Requires-Dist: numpy
Requires-Dist: scipy
Requires-Dist: webvtt-py
Requires-Dist: moviepy
